kantris/Basics.py
kantris/Calc.py
kantris/DataManipulation.py
kantris/FFT.py
kantris/HTTP.py
kantris/PCA.py
kantris/Progressive_CWT.py
kantris/STFT.py
kantris/Transformations.py
kantris/__init__.py
kantris/plotter.py
kantris-0.4.2.dist-info/METADATA
kantris-0.4.2.dist-info/WHEEL
kantris-0.4.2.dist-info/top_level.txt
kantris-0.4.2.dist-info/RECORD
