Metadata-Version: 2.4
Name: kantris
Version: 0.4.2
Summary: Kantris Framework
Author: Teryces
License: MIT
Classifier: Programming Language :: Python :: 3
Classifier: License :: OSI Approved :: MIT License
Classifier: Operating System :: OS Independent
